securedb/__init__.py
securedb/connections.py
securedb/core.py
securedb/utils.py
smart_securedb-1.0.0.dist-info/licenses/LICENSE
smart_securedb-1.0.0.dist-info/METADATA
smart_securedb-1.0.0.dist-info/WHEEL
smart_securedb-1.0.0.dist-info/top_level.txt
smart_securedb-1.0.0.dist-info/RECORD
