Metadata-Version: 2.4
Name: smart-securedb
Version: 1.0.0
Summary: A secure, parameterized database access layer to prevent SQL injection and ensure safe multi-database access.
Author-email: Rejith Kumar <rejithsham296@outlook.com>
License: MIT License
Project-URL: Homepage, https://bitbucket.org/RejithkumarIT/pypi-packages/src/develop/smart-securedb
Project-URL: Repository, https://bitbucket.org/RejithkumarIT/pypi-packages/src/develop/smart-securedb
Project-URL: Issues, https://bitbucket.org/RejithkumarIT/pypi-packages/src/develop/smart-securedb
Keywords: secure,database,sql,sqlalchemy,security,injection,parameterized,safe,mysql,oracle,postgresql,mssql
Classifier: Programming Language :: Python :: 3
Classifier: Programming Language :: Python :: 3.8
Classifier: Programming Language :: Python :: 3.9
Classifier: Programming Language :: Python :: 3.10
Classifier: Topic :: Database
Classifier: Topic :: Security
Classifier: License :: OSI Approved :: MIT License
Classifier: Operating System :: OS Independent
Requires-Python: >=3.8
License-File: LICENSE
Requires-Dist: SQLAlchemy>=2.0.0
Requires-Dist: cryptography>=42.0.0
Requires-Dist: smart-encryptor>=1.0.0
Dynamic: license-file
